{"Generation":1,"NNS":[{"C":[{"active":true,"from":94,"to":122,"w":0.6811000108718872}]},{"C":[{"active":true,"from":97,"to":122,"w":0.9629999995231628}]},{"C":[{"active":true,"from":90,"to":122,"w":0.18320000171661377}]},null,null,{"C":[{"active":true,"from":12,"to":122,"w":0.4291999936103821}]},{"C":[{"active":true,"from":86,"to":123,"w":-0.2896000146865845}]},{"C":[{"active":true,"from":65,"to":122,"w":0.4738999903202057}]},null,{"C":[{"active":true,"from":61,"to":123,"w":0.28189998865127563}]},null,{"C":[{"active":true,"from":29,"to":122,"w":-0.6845999956130981}]},{"C":[{"active":true,"from":86,"to":122,"w":-0.3393999934196472}]},{"C":[{"active":true,"from":114,"to":122,"w":0.050700001418590546}]},{"C":[{"active":true,"from":62,"to":122,"w":0.6340000033378601}]},{"C":[{"active":true,"from":65,"to":123,"w":-0.32089999318122864}]},{"C":[{"active":true,"from":10,"to":123,"w":-0.6449999809265137}]},null,{"C":[{"active":true,"from":91,"to":123,"w":-0.5655999779701233}]},{"C":[{"active":true,"from":30,"to":122,"w":-0.1031000018119812}]},{"C":[{"active":true,"from":51,"to":122,"w":0.7728000283241272}]},{"C":[{"active":true,"from":8,"to":123,"w":-0.8902999758720398}]},{"C":[{"active":true,"from":106,"to":123,"w":0.9381999969482422}]},{"C":[{"active":true,"from":88,"to":123,"w":-0.5978999733924866}]},{"C":[{"active":true,"from":98,"to":122,"w":-0.18970000743865967}]},{"C":[{"active":true,"from":62,"to":122,"w":-0.8906000256538391}]},{"C":[{"active":true,"from":20,"to":123,"w":-0.10459999740123749}]},{"C":[{"active":true,"from":47,"to":122,"w":-0.12370000034570694}]},{"C":[{"active":true,"from":9,"to":122,"w":0.9067999720573425}]},{"C":[{"active":true,"from":67,"to":123,"w":0.1014999970793724}]},{"C":[{"active":true,"from":32,"to":122,"w":-0.13830000162124634}]},{"C":[{"active":true,"from":87,"to":122,"w":-0.44359999895095825}]},{"C":[{"active":true,"from":26,"to":123,"w":-0.8339999914169312}]},{"C":[{"active":true,"from":10,"to":122,"w":0.5928999781608582}]},{"C":[{"active":true,"from":33,"to":122,"w":-0.23280000686645508}]},{"C":[{"active":true,"from":67,"to":123,"w":-0.8381999731063843}]},{"C":[{"active":true,"from":12,"to":122,"w":0.3109999895095825}]},{"C":[{"active":true,"from":78,"to":122,"w":-0.9872999787330627}]},{"C":[{"active":true,"from":71,"to":122,"w":-0.527899980545044}]},{"C":[{"active":true,"from":45,"to":122,"w":0.29670000076293945}]},{"C":[{"active":true,"from":15,"to":122,"w":0.34869998693466187}]},{"C":[{"active":true,"from":0,"to":123,"w":0.2011999934911728}]},{"C":[{"active":true,"from":81,"to":123,"w":0.26260000467300415}]},{"C":[{"active":true,"from":41,"to":122,"w":0.19619999825954437}]},{"C":[{"active":true,"from":95,"to":123,"w":-0.3792000114917755}]},{"C":[{"active":true,"from":75,"to":122,"w":-0.43560001254081726}]},{"C":[{"active":true,"from":87,"to":122,"w":-0.09600000083446503}]},{"C":[{"active":true,"from":118,"to":123,"w":-0.7121000289916992}]},{"C":[{"active":true,"from":87,"to":123,"w":0.010099999606609344}]},{"C":[{"active":true,"from":94,"to":122,"w":0.21230000257492065}]},{"C":[{"active":true,"from":70,"to":122,"w":0.7229999899864197}]},{"C":[{"active":true,"from":16,"to":123,"w":-0.47540000081062317}]},{"C":[{"active":true,"from":110,"to":123,"w":-0.1889999955892563}]},{"C":[{"active":true,"from":15,"to":122,"w":-0.45179998874664307}]},{"C":[{"active":true,"from":84,"to":122,"w":0.927299976348877}]},{"C":[{"active":true,"from":50,"to":123,"w":-0.17270000278949738}]},{"C":[{"active":true,"from":106,"to":122,"w":-0.24480000138282776}]},{"C":[{"active":true,"from":75,"to":122,"w":-0.7728999853134155}]},{"C":[{"active":true,"from":4,"to":123,"w":-0.15379999577999115}]},{"C":[{"active":true,"from":107,"to":122,"w":-0.03920000046491623}]},{"C":[{"active":true,"from":48,"to":123,"w":0.14749999344348907}]},{"C":[{"active":true,"from":103,"to":123,"w":0.9474999904632568}]},{"C":[{"active":true,"from":118,"to":123,"w":-0.2705000042915344}]},{"C":[{"active":true,"from":105,"to":123,"w":0.6262000203132629}]},{"C":[{"active":true,"from":36,"to":123,"w":-0.45890000462532043}]},{"C":[{"active":true,"from":51,"to":122,"w":-0.9851999878883362}]},{"C":[{"active":true,"from":46,"to":122,"w":0.5315999984741211}]},{"C":[{"active":true,"from":97,"to":122,"w":0.15559999644756317}]},{"C":[{"active":true,"from":34,"to":123,"w":-0.583899974822998}]},{"C":[{"active":true,"from":61,"to":123,"w":-0.833299994468689}]},{"C":[{"active":true,"from":1,"to":122,"w":0.698199987411499}]},{"C":[{"active":true,"from":117,"to":122,"w":-0.9605000019073486}]},{"C":[{"active":true,"from":9,"to":123,"w":0.5665000081062317}]},{"C":[{"active":true,"from":46,"to":122,"w":-0.9818999767303467}]},{"C":[{"active":true,"from":25,"to":123,"w":-0.5067999958992004}]},{"C":[{"active":true,"from":36,"to":122,"w":-0.8978999853134155}]},{"C":[{"active":true,"from":27,"to":123,"w":0.42829999327659607}]},{"C":[{"active":true,"from":38,"to":122,"w":-0.4636000096797943}]},{"C":[{"active":true,"from":118,"to":122,"w":0.26570001244544983}]},{"C":[{"active":true,"from":7,"to":123,"w":-0.9829000234603882}]},{"C":[{"active":true,"from":81,"to":123,"w":0.20069999992847443}]},{"C":[{"active":true,"from":106,"to":123,"w":-0.15489999949932098}]},{"C":[{"active":true,"from":46,"to":123,"w":0.6144000291824341}]},{"C":[{"active":true,"from":90,"to":123,"w":-0.9241999983787537}]},{"C":[{"active":true,"from":69,"to":122,"w":0.6960999965667725}]},{"C":[{"active":true,"from":104,"to":123,"w":-0.2101999968290329}]},{"C":[{"active":true,"from":102,"to":123,"w":-0.9057000279426575}]},{"C":[{"active":true,"from":35,"to":123,"w":-0.35530000925064087}]},{"C":[{"active":true,"from":116,"to":122,"w":-0.8740000128746033}]},{"C":[{"active":true,"from":93,"to":123,"w":-0.10679999738931656}]},{"C":[{"active":true,"from":92,"to":122,"w":0.5194000005722046}]},{"C":[{"active":true,"from":98,"to":122,"w":0.7232000231742859}]},{"C":[{"active":true,"from":86,"to":122,"w":0.7903000116348267}]},{"C":[{"active":true,"from":43,"to":122,"w":-0.3197999894618988}]},{"C":[{"active":true,"from":100,"to":123,"w":-0.40700000524520874}]},{"C":[{"active":true,"from":43,"to":122,"w":-0.07720000296831131}]},{"C":[{"active":true,"from":104,"to":123,"w":-0.9690999984741211}]},{"C":[{"active":true,"from":104,"to":122,"w":0.5870000123977661}]},{"C":[{"active":true,"from":97,"to":122,"w":0.7148000001907349}]},{"C":[{"active":true,"from":95,"to":123,"w":-0.6223999857902527}]},{"C":[{"active":true,"from":9,"to":123,"w":-0.2946999967098236}]},{"C":[{"active":true,"from":91,"to":122,"w":-0.9805999994277954}]},{"C":[{"active":true,"from":15,"to":123,"w":0.25279998779296875}]},{"C":[{"active":true,"from":89,"to":122,"w":0.1143999993801117}]},{"C":[{"active":true,"from":78,"to":122,"w":-0.14470000565052032}]},{"C":[{"active":true,"from":88,"to":123,"w":-0.17759999632835388}]},{"C":[{"active":true,"from":45,"to":122,"w":-0.006800000090152025}]},{"C":[{"active":true,"from":72,"to":123,"w":-0.31779998540878296}]},{"C":[{"active":true,"from":31,"to":122,"w":-0.10719999670982361}]},{"C":[{"active":true,"from":102,"to":123,"w":-0.7797999978065491}]},{"C":[{"active":true,"from":18,"to":123,"w":0.23119999468326569}]},{"C":[{"active":true,"from":58,"to":122,"w":-0.9968000054359436}]},{"C":[{"active":true,"from":27,"to":122,"w":-0.358599990606308}]},{"C":[{"active":true,"from":63,"to":122,"w":0.5960999727249146}]},{"C":[{"active":true,"from":91,"to":122,"w":-0.6830000281333923}]},{"C":[{"active":true,"from":85,"to":122,"w":-0.6255000233650208}]},{"C":[{"active":true,"from":40,"to":122,"w":0.0640999972820282}]},{"C":[{"active":true,"from":42,"to":122,"w":-0.13189999759197235}]},{"C":[{"active":true,"from":19,"to":123,"w":0.8424999713897705}]},{"C":[{"active":true,"from":113,"to":123,"w":0.6468999981880188}]},{"C":[{"active":true,"from":25,"to":123,"w":0.8476999998092651}]},{"C":[{"active":true,"from":11,"to":122,"w":0.25690001249313354}]},{"C":[{"active":true,"from":103,"to":122,"w":-0.9308000206947327}]},{"C":[{"active":true,"from":95,"to":122,"w":-0.01600000075995922}]},{"C":[{"active":true,"from":99,"to":123,"w":-0.4968999922275543}]},{"C":[{"active":true,"from":25,"to":123,"w":0.1421000063419342}]},{"C":[{"active":true,"from":76,"to":122,"w":-0.12860000133514404}]},{"C":[{"active":true,"from":38,"to":122,"w":-0.9706000089645386}]},{"C":[{"active":true,"from":35,"to":123,"w":-0.06129999831318855}]},{"C":[{"active":true,"from":121,"to":123,"w":0.2653000056743622}]},{"C":[{"active":true,"from":65,"to":123,"w":0.6151000261306763}]},{"C":[{"active":true,"from":15,"to":123,"w":0.13650000095367432}]},{"C":[{"active":true,"from":59,"to":123,"w":0.48579999804496765}]},{"C":[{"active":true,"from":24,"to":122,"w":-0.5327000021934509}]},{"C":[{"active":true,"from":40,"to":122,"w":0.09860000014305115}]},{"C":[{"active":true,"from":71,"to":123,"w":-0.313400000333786}]},{"C":[{"active":true,"from":76,"to":123,"w":0.22339999675750732}]},{"C":[{"active":true,"from":114,"to":123,"w":-0.25949999690055847}]},{"C":[{"active":true,"from":74,"to":122,"w":-0.5370000004768372}]},{"C":[{"active":true,"from":27,"to":122,"w":-0.5769000053405762}]},{"C":[{"active":true,"from":110,"to":122,"w":-0.6086999773979187}]},{"C":[{"active":true,"from":16,"to":123,"w":-0.6948999762535095}]},{"C":[{"active":true,"from":120,"to":123,"w":-0.3650999963283539}]},{"C":[{"active":true,"from":97,"to":122,"w":0.7368999719619751}]},{"C":[{"active":true,"from":3,"to":122,"w":-0.31119999289512634}]},{"C":[{"active":true,"from":101,"to":122,"w":-0.6448000073432922}]},{"C":[{"active":true,"from":39,"to":123,"w":-0.4936999976634979}]},{"C":[{"active":true,"from":56,"to":123,"w":-0.24799999594688416}]},{"C":[{"active":true,"from":70,"to":122,"w":0.06289999932050705}]},{"C":[{"active":true,"from":65,"to":123,"w":-0.9072999954223633}]},{"C":[{"active":true,"from":88,"to":122,"w":-0.8590999841690063}]},{"C":[{"active":true,"from":90,"to":122,"w":-0.7616000175476074}]},{"C":[{"active":true,"from":17,"to":122,"w":-0.30160000920295715}]},{"C":[{"active":true,"from":77,"to":122,"w":-0.6854000091552734}]},{"C":[{"active":true,"from":118,"to":122,"w":-0.9351999759674072}]},{"C":[{"active":true,"from":6,"to":123,"w":-0.5734000205993652}]},{"C":[{"active":true,"from":74,"to":123,"w":-0.38339999318122864}]},{"C":[{"active":true,"from":93,"to":123,"w":-0.46160000562667847}]},{"C":[{"active":true,"from":18,"to":122,"w":0.5133000016212463}]},{"C":[{"active":true,"from":72,"to":122,"w":-0.01140000019222498}]},{"C":[{"active":true,"from":13,"to":122,"w":-0.9799000024795532}]},{"C":[{"active":true,"from":57,"to":122,"w":-0.364300012588501}]},{"C":[{"active":true,"from":113,"to":123,"w":0.9060999751091003}]},{"C":[{"active":true,"from":68,"to":122,"w":-0.3199000060558319}]},{"C":[{"active":true,"from":85,"to":122,"w":-0.7422000169754028}]},{"C":[{"active":true,"from":14,"to":123,"w":0.8144000172615051}]},{"C":[{"active":true,"from":56,"to":122,"w":-0.46320000290870667}]},{"C":[{"active":true,"from":115,"to":123,"w":-0.03700000047683716}]},{"C":[{"active":true,"from":87,"to":123,"w":0.17599999904632568}]},{"C":[{"active":true,"from":5,"to":122,"w":0.7739999890327454}]},{"C":[{"active":true,"from":20,"to":122,"w":-0.305400013923645}]},{"C":[{"active":true,"from":108,"to":123,"w":0.8450000286102295}]},{"C":[{"active":true,"from":25,"to":123,"w":-0.03400000184774399}]},{"C":[{"active":true,"from":101,"to":122,"w":0.2304999977350235}]},{"C":[{"active":true,"from":101,"to":122,"w":0.06599999964237213}]},{"C":[{"active":true,"from":29,"to":122,"w":0.04450000077486038}]},{"C":[{"active":true,"from":66,"to":122,"w":0.8880000114440918}]},{"C":[{"active":true,"from":5,"to":123,"w":0.5514000058174133}]},{"C":[{"active":true,"from":110,"to":122,"w":0.48030000925064087}]},{"C":[{"active":true,"from":87,"to":122,"w":-0.7901999950408936}]},{"C":[{"active":true,"from":5,"to":123,"w":-0.6237000226974487}]},{"C":[{"active":true,"from":50,"to":123,"w":0.2624000012874603}]},{"C":[{"active":true,"from":54,"to":123,"w":0.13670000433921814}]},{"C":[{"active":true,"from":92,"to":122,"w":-0.40630000829696655}]},{"C":[{"active":true,"from":41,"to":122,"w":-0.5914999842643738}]},{"C":[{"active":true,"from":29,"to":123,"w":-0.15080000460147858}]},{"C":[{"active":true,"from":85,"to":123,"w":-0.6883999705314636}]},{"C":[{"active":true,"from":53,"to":122,"w":0.45829999446868896}]},{"C":[{"active":true,"from":4,"to":122,"w":-0.14560000598430634}]},{"C":[{"active":true,"from":49,"to":123,"w":-0.5615000128746033}]},{"C":[{"active":true,"from":2,"to":122,"w":0.453000009059906}]},{"C":[{"active":true,"from":107,"to":123,"w":0.6015999913215637}]},{"C":[{"active":true,"from":15,"to":123,"w":-0.7789000272750854}]},{"C":[{"active":true,"from":42,"to":123,"w":-0.22910000383853912}]},{"C":[{"active":true,"from":75,"to":122,"w":-0.3109000027179718}]},{"C":[{"active":true,"from":2,"to":123,"w":0.23970000445842743}]},{"C":[{"active":true,"from":62,"to":122,"w":0.7178999781608582}]},{"C":[{"active":true,"from":23,"to":122,"w":0.16500000655651093}]},{"C":[{"active":true,"from":5,"to":123,"w":-0.513700008392334}]},{"C":[{"active":true,"from":3,"to":122,"w":0.8306999802589417}]}]}